[
  {
    "version": "main",
    "url": "https://eclipse-score.github.io/inc_someip_gateway/main/"
  },
  {
    "version": "pr-100",
    "url": "https://eclipse-score.github.io/inc_someip_gateway/pr-100/"
  },
  {
    "version": "pr-126",
    "url": "https://eclipse-score.github.io/inc_someip_gateway/pr-126/"
  },
  {
    "version": "pr-141",
    "url": "https://eclipse-score.github.io/inc_someip_gateway/pr-141/"
  },
  {
    "version": "pr-149",
    "url": "https://eclipse-score.github.io/inc_someip_gateway/pr-149/"
  },
  {
    "version": "pr-15",
    "url": "https://eclipse-score.github.io/inc_someip_gateway/pr-15/"
  },
  {
    "version": "pr-151",
    "url": "https://eclipse-score.github.io/inc_someip_gateway/pr-151/"
  },
  {
    "version": "pr-152",
    "url": "https://eclipse-score.github.io/inc_someip_gateway/pr-152/"
  },
  {
    "version": "pr-60",
    "url": "https://eclipse-score.github.io/inc_someip_gateway/pr-60/"
  },
  {
    "version": "pr-86",
    "url": "https://eclipse-score.github.io/inc_someip_gateway/pr-86/"
  },
  {
    "version": "pr-98",
    "url": "https://eclipse-score.github.io/inc_someip_gateway/pr-98/"
  }
]
